<package>
  <description brief="experiments">

     experiments

  </description>
  <author>Steve Safarik</author>
  <license>BSD</license>
  <review status="unreviewed" notes=""/>
  <url>http://ros.org/wiki/experiments</url>

  <depend package="rospy"/>
  <depend package="geometry_msgs"/>
  <depend package="std_msgs"/>
  <depend package="actionlib"/>
  <depend package="smach"/>
  <depend package="smach_ros"/>
  <depend package="visualization_msgs"/>

  <depend package="config" />
  <depend package="flycore" />
  <depend package="galvodirector" />
  <depend package="LEDPanels" />
  <depend package="patterngen" />
  <depend package="stage_action_server" />
  <depend package="tracking" />
 
</package>


